deepsearch_glm/__init__.py
deepsearch_glm/andromeda_glm.cpython-39-darwin.so
deepsearch_glm/andromeda_nlp.cpython-39-darwin.so
deepsearch_glm/andromeda_structs.cpython-39-darwin.so
deepsearch_glm/glm_create_from_docs.py
deepsearch_glm/glm_docqa.py
deepsearch_glm/glm_explore.py
deepsearch_glm/glm_query.py
deepsearch_glm/glm_utils.py
deepsearch_glm/nlp_analyse_docs.py
deepsearch_glm/nlp_apply_on_docs.py
deepsearch_glm/nlp_apply_on_text.py
deepsearch_glm/nlp_model_training/__init__.py
deepsearch_glm/nlp_model_training/name_classifier.py
deepsearch_glm/nlp_model_training/person_name_classifier.py
deepsearch_glm/nlp_model_training/reference_parsing.py
deepsearch_glm/nlp_model_training/semantic_classifier.py
deepsearch_glm/nlp_train_crf.py
deepsearch_glm/nlp_train_tok.py
deepsearch_glm/nlp_utils.py
deepsearch_glm/resources/confusables/confusablesRestricted.txt
deepsearch_glm/resources/confusables/confusablesSummary.txt
deepsearch_glm/resources/confusables/note.txt
deepsearch_glm/resources/data/nlp/note.md
deepsearch_glm/resources/data/text/note.md
deepsearch_glm/resources/data.json
deepsearch_glm/resources/data_nlp/note.md
deepsearch_glm/resources/models/crf/geoloc/note.md
deepsearch_glm/resources/models/crf/part-of-speech/note.md
deepsearch_glm/resources/models/crf/reference/note.md
deepsearch_glm/resources/models/crf/ucmi/note.md
deepsearch_glm/resources/models/fasttext/language/note.md
deepsearch_glm/resources/models/fasttext/metadata/note.md
deepsearch_glm/resources/models/fasttext/person-name/note.md
deepsearch_glm/resources/models/fasttext/semantic/note.md
deepsearch_glm/resources/models/fasttext/topic/note.md
deepsearch_glm/resources/models/rgx/geoloc/note.md
deepsearch_glm/resources/models/rgx/vau/units.jsonl
deepsearch_glm/resources/models/tok/default-tokenizer.model
deepsearch_glm/resources/models/tok/note.md
deepsearch_glm/resources/models.json
deepsearch_glm/utils/__init__.py
deepsearch_glm/utils/common.py
deepsearch_glm/utils/doc_utils.py
deepsearch_glm-0.26.2.dist-info/LICENSE
deepsearch_glm-0.26.2.dist-info/METADATA
deepsearch_glm-0.26.2.dist-info/WHEEL
deepsearch_glm-0.26.2.dist-info/RECORD
