Metadata-Version: 2.1
Name: deepsearch-glm
Version: 0.26.2
Summary: Graph Language Models
License: MIT
Author: Peter Staar
Author-email: taa@zurich.ibm.com
Requires-Python: >=3.9,<4.0
Classifier: License :: OSI Approved :: MIT License
Classifier: Programming Language :: Python :: 3
Classifier: Programming Language :: Python :: 3.9
Classifier: Programming Language :: Python :: 3.10
Classifier: Programming Language :: Python :: 3.11
Classifier: Programming Language :: Python :: 3.12
Provides-Extra: pyplot
Provides-Extra: toolkit
Requires-Dist: deepsearch-toolkit (>=1.1.0,<2.0.0) ; extra == "toolkit"
Requires-Dist: docling-core (>=2.0,<3.0)
Requires-Dist: docutils (!=0.21)
Requires-Dist: matplotlib (>=3.7.1,<4.0.0) ; extra == "pyplot"
Requires-Dist: numpy (>=1.24.4,<3.0.0)
Requires-Dist: pandas (>=1.5.1,<3.0.0)
Requires-Dist: python-dotenv (>=1.0.0,<2.0.0)
Requires-Dist: pywin32 (>=307,<308) ; sys_platform == "win32"
Requires-Dist: requests (>=2.32.3,<3.0.0)
Requires-Dist: rich (>=13.7.0,<14.0.0)
Requires-Dist: tabulate (>=0.8.9)
Requires-Dist: tqdm (>=4.64.0,<5.0.0)
